QuantStudio/__init__.py
QuantStudio/api.py
QuantStudio/BackTest/BackTestModel.py
QuantStudio/BackTest/__init__.py
QuantStudio/BackTest/api.py
QuantStudio/BackTest/Event/AbnormalReturn.py
QuantStudio/BackTest/Event/__init__.py
QuantStudio/BackTest/Event/api.py
QuantStudio/BackTest/PerformanceAnalysis/BrinsonModel.py
QuantStudio/BackTest/PerformanceAnalysis/FMPModel.py
QuantStudio/BackTest/PerformanceAnalysis/__init__.py
QuantStudio/BackTest/PerformanceAnalysis/api.py
QuantStudio/BackTest/SectionFactor/Correlation.py
QuantStudio/BackTest/SectionFactor/Distribution.py
QuantStudio/BackTest/SectionFactor/IC.py
QuantStudio/BackTest/SectionFactor/Portfolio.py
QuantStudio/BackTest/SectionFactor/ReturnDecomposition.py
QuantStudio/BackTest/SectionFactor/__init__.py
QuantStudio/BackTest/SectionFactor/api.py
QuantStudio/BackTest/Strategy/BondAccount.py
QuantStudio/BackTest/Strategy/CloverAccount.py
QuantStudio/BackTest/Strategy/DefaultAccount.py
QuantStudio/BackTest/Strategy/ETFAccount.py
QuantStudio/BackTest/Strategy/FutureAccount.py
QuantStudio/BackTest/Strategy/MarginAccount.py
QuantStudio/BackTest/Strategy/PortfolioStrategy.py
QuantStudio/BackTest/Strategy/SimpleAccount.py
QuantStudio/BackTest/Strategy/StockAccount.py
QuantStudio/BackTest/Strategy/StrategyModule.py
QuantStudio/BackTest/Strategy/TimingStrategy.py
QuantStudio/BackTest/Strategy/__init__.py
QuantStudio/BackTest/Strategy/api.py
QuantStudio/BackTest/TimeSeriesFactor/Correlation.py
QuantStudio/BackTest/TimeSeriesFactor/Difference.py
QuantStudio/BackTest/TimeSeriesFactor/Regression.py
QuantStudio/BackTest/TimeSeriesFactor/Spread.py
QuantStudio/BackTest/TimeSeriesFactor/__init__.py
QuantStudio/BackTest/TimeSeriesFactor/api.py
QuantStudio/EventDrivenBackTest/BackTestModel.py
QuantStudio/EventDrivenBackTest/__init__.py
QuantStudio/EventDrivenBackTest/api.py
QuantStudio/EventDrivenBackTest/SectionFactor/IC.py
QuantStudio/EventDrivenBackTest/SectionFactor/__init__.py
QuantStudio/EventDrivenBackTest/SectionFactor/api.py
QuantStudio-0.0.9.dist-info/LICENSE
QuantStudio-0.0.9.dist-info/METADATA
QuantStudio-0.0.9.dist-info/WHEEL
QuantStudio-0.0.9.dist-info/top_level.txt
QuantStudio-0.0.9.dist-info/RECORD
