Metadata-Version: 2.1
Name: QuantStudio
Version: 0.0.9
Summary: Quant Studio
Home-page: https://github.com/Scorpi000/QuantStudio/
Author: scorpi000
Author-email: scorpi000@sina.cn
Maintainer: scorpi000
Maintainer-email: scorpi000@sina.cn
License: GPLv3
Platform: Windows
Classifier: Programming Language :: Python :: 3
Classifier: License :: OSI Approved :: GNU General Public License v3 (GPLv3)
Classifier: Operating System :: OS Independent
Classifier: Topic :: Office/Business :: Financial :: Investment
Requires-Python: >=3.5
Requires-Dist: numpy (>=1.14.4+mkl)
Requires-Dist: numexpr (>=2.6.1)
Requires-Dist: pandas (<0.24.0,>=0.19.0)
Requires-Dist: scipy (>=0.18.1)
Requires-Dist: matplotlib (>=2.2.3)
Requires-Dist: seaborn (>=0.9.0)
Requires-Dist: plotly (>=2.0.6)
Requires-Dist: patsy
Requires-Dist: statsmodels (>=0.9.0)
Requires-Dist: h5py (>=2.6.0)
Requires-Dist: cx-Oracle (>=5.2.1)
Requires-Dist: pymssql (>=2.1.3)
Requires-Dist: mysql-connector-python
Requires-Dist: pyodbc (>=4.0.14)
Requires-Dist: pymongo (>=3.4.0)
Requires-Dist: arctic (>=1.67.0)
Requires-Dist: chardet (>=3.0.4)
Requires-Dist: progressbar2 (>=3.10.1)
Requires-Dist: fasteners (>=0.14.0)
Requires-Dist: pyface (>=6.0.0)
Requires-Dist: traits (>=4.6.0)
Requires-Dist: traitsui (>=6.0.0)
Requires-Dist: bs4 (>=0.0.1)
Requires-Dist: tushare (>=1.2.12)
Requires-Dist: xlrd (>=0.9.0)
Requires-Dist: xlwt (>=1.3.0)
Requires-Dist: PyQt5 (>=5.9.2)
